espydio/__init__.py
espydio/audioFileDetails.py
espydio/formatConversion.py
espydio/script_espydio.py
espydio/streamAudio.py
espydio/textToMP3.py
espydio/wavToHex.py
espydio-0.0.3.dist-info/LICENSE.txt
espydio-0.0.3.dist-info/METADATA
espydio-0.0.3.dist-info/WHEEL
espydio-0.0.3.dist-info/entry_points.txt
espydio-0.0.3.dist-info/top_level.txt
espydio-0.0.3.dist-info/RECORD
