Metadata-Version: 2.1
Name: espydio
Version: 0.0.3
Summary: A command line utility built using python to automate audio file conversions, thereby assisting audio playing on ESP32
Home-page: https://github.com/namanPuri/espydio
Author: Naman Puri
Author-email: namanpuri1712@gmail.com
License: BSD-3-Clause
Keywords: esp32 sound conversions
Platform: UNKNOWN
Classifier: Intended Audience :: Developers
Classifier: License :: OSI Approved :: MIT License
Classifier: Operating System :: Microsoft :: Windows
Classifier: Programming Language :: Python :: 3
Classifier: Topic :: Utilities
License-File: LICENSE.txt
Requires-Dist: Flask (==1.1.2)
Requires-Dist: sox (==1.4.1)
Requires-Dist: requests (==2.25.1)
